SeleniumHelperLibrary/__init__.py
SeleniumHelperLibrary/attribute.py
SeleniumHelperLibrary/button.py
SeleniumHelperLibrary/click.py
SeleniumHelperLibrary/frame.py
SeleniumHelperLibrary/helper.py
SeleniumHelperLibrary/input.py
SeleniumHelperLibrary/link.py
SeleniumHelperLibrary/select.py
SeleniumHelperLibrary/text.py
SeleniumHelperLibrary/textarea.py
SeleniumHelperLibrary/title.py
SeleniumHelperLibrary/util.py
SeleniumHelperLibrary/version.py
SeleniumHelperLibrary/wait.py
SeleniumHelperLibrary/web_element.py
robotframework_seleniumhelperlibrary-0.1.8.dist-info/LICENSE
robotframework_seleniumhelperlibrary-0.1.8.dist-info/METADATA
robotframework_seleniumhelperlibrary-0.1.8.dist-info/WHEEL
robotframework_seleniumhelperlibrary-0.1.8.dist-info/top_level.txt
robotframework_seleniumhelperlibrary-0.1.8.dist-info/RECORD
