Metadata-Version: 2.1
Name: robotframework-seleniumhelperlibrary
Version: 0.1.8
Summary: Helper keywords for robotframework-selenium
Home-page: https://github.com/adiralashiva8/robotframework-seleniumhelperlibrary
Author: Shiva Adirala
Author-email: adiralashiva8@gmail.com
License: MIT
Keywords: Helper keywords for robotframework-selenium
Platform: any
Classifier: Operating System :: OS Independent
Classifier: Programming Language :: Python
Classifier: Topic :: Software Development :: Testing
License-File: LICENSE
Requires-Dist: robotframework
Requires-Dist: robotframework-seleniumlibrary
